excel_graph_api/__init__.py
excel_graph_api/client.py
excel_graph_api-1.0.0.dist-info/licenses/LICENSE
excel_graph_api-1.0.0.dist-info/METADATA
excel_graph_api-1.0.0.dist-info/WHEEL
excel_graph_api-1.0.0.dist-info/top_level.txt
excel_graph_api-1.0.0.dist-info/RECORD
