Metadata-Version: 2.4
Name: excel-graph-api
Version: 1.0.0
Summary: Read and write Excel files in OneDrive using Microsoft Graph API
Author: Maxspike Capital
License: MIT
Project-URL: Homepage, https://github.com/maxspike/excel-graph-api
Keywords: excel,onedrive,microsoft,graph,api,spreadsheet
Classifier: Development Status :: 4 - Beta
Classifier: Intended Audience :: Developers
Classifier: License :: OSI Approved :: MIT License
Classifier: Operating System :: OS Independent
Classifier: Programming Language :: Python :: 3
Classifier: Programming Language :: Python :: 3.7
Classifier: Programming Language :: Python :: 3.8
Classifier: Programming Language :: Python :: 3.9
Classifier: Programming Language :: Python :: 3.10
Classifier: Programming Language :: Python :: 3.11
Classifier: Programming Language :: Python :: 3.12
Classifier: Topic :: Office/Business :: Office Suites
Requires-Python: >=3.7
License-File: LICENSE
Requires-Dist: requests>=2.25.0
Dynamic: license-file
